ingestor/__init__.py
ingestor/common/__init__.py
ingestor/common/constants.py
ingestor/common/convert_time_zone.py
ingestor/common/dump_static_data.py
ingestor/common/preprocessing_utils.py
ingestor/common/read_write_from_s3.py
ingestor/common/static_node_generator.py
ingestor/content_profile/__init__.py
ingestor/content_profile/config.py
ingestor/content_profile/network/__init__.py
ingestor/content_profile/network/content.py
ingestor/content_profile/network/content_utils.py
ingestor/merge_df/__init__.py
ingestor/merge_df/common.py
ingestor/merge_df/content.py
ingestor/merge_df/ubd.py
ingestor/merge_df/ubd_mapping.py
ingestor/merge_df/user.py
ingestor/rce_user_cluster/__init__.py
ingestor/repository/__init__.py
ingestor/repository/graph_db_connection.py
ingestor/sample/__init__.py
ingestor/sample/gremlin_network_example.py
ingestor/sample/ingestor.py
ingestor/user_content_network/__init__.py
ingestor/user_content_network/update_viewed.py
ingestor/user_content_network/utils.py
ingestor/user_profile/__init__.py
ingestor/user_profile/constants.py
ingestor/user_profile/main/__init__.py
ingestor/user_profile/main/config.py
ingestor/user_profile/main/post_offline.py
ingestor/user_profile/main/pre_offline.py
ingestor/user_profile/main/streaming_users.py
ingestor/user_profile/network/__init__.py
ingestor/user_profile/network/plot_relations.py
ingestor/user_profile/network/user_node_generator.py
ingestor/user_profile/preferences/__init__.py
ingestor/user_profile/preferences/generate_preferences.py
ingestor/user_profile/preferences/relationship_extractor.py
ingestor/user_profile/preferences/viewtime_preferences.py
ingestor/user_profile/preprocessing/__init__.py
ingestor/user_profile/preprocessing/behaviour.py
ingestor/user_profile/preprocessing/demographics.py
ingestor/user_profile/streaming_clustering/__init__.py
ingestor/user_profile/streaming_clustering/cluster_allocator_controller.py
ingestor/user_profile/streaming_clustering/cluster_allocator_utils.py
ingestor_module-1.17.4.dist-info/WHEEL
ingestor_module-1.17.4.dist-info/METADATA
ingestor_module-1.17.4.dist-info/RECORD
