Metadata-Version: 2.1
Name: ingestor-module
Version: 1.17.4
Summary: 
License: MIT
Author: AIML Team
Requires-Python: >=3.8,<3.11
Classifier: License :: OSI Approved :: MIT License
Classifier: Programming Language :: Python :: 3
Classifier: Programming Language :: Python :: 3.8
Classifier: Programming Language :: Python :: 3.9
Classifier: Programming Language :: Python :: 3.10
Classifier: Programming Language :: Python :: 3
Classifier: Programming Language :: Python :: 3.10
Classifier: Programming Language :: Python :: 3.11
Classifier: Programming Language :: Python :: 3.7
Classifier: Programming Language :: Python :: 3.8
Classifier: Programming Language :: Python :: 3.9
Requires-Dist: Sastrawi (>=1.0.1,<2.0.0)
Requires-Dist: boto3 (>=1.20.50,<2.0.0)
Requires-Dist: graphdb-module (>=0.12.14,<0.13.0)
Requires-Dist: networkx (>=2.8.5,<3.0.0)
Requires-Dist: nltk (>=3.7,<4.0)
Requires-Dist: numpy (>=1.22.1,<2.0.0)
Requires-Dist: pandas (>=1.4.0,<2.0.0)
Requires-Dist: scikit-learn (>=1.0.2,<2.0.0)
Requires-Dist: setuptools (>=59.1.1,<60.0.0)
